arsa/__init__.py
arsa-1.2.0.dist-info/LICENSE
arsa-1.2.0.dist-info/METADATA
arsa-1.2.0.dist-info/WHEEL
arsa-1.2.0.dist-info/top_level.txt
arsa-1.2.0.dist-info/RECORD
