Metadata-Version: 2.1
Name: arsa
Version: 1.2.0
Summary: A multilingual RSA library with segmented encryption and decryption and a unified format.
Home-page: https://github.com/ATATC/ARSA
Author: ATATC
Author-email: futerry@outlook.com
Maintainer: ATATC
Maintainer-email: futerry@outlook.com
License: MIT License
Platform: all
Classifier: Operating System :: OS Independent
Classifier: Intended Audience :: Developers
Classifier: License :: OSI Approved :: MIT License
Classifier: Programming Language :: Python
Classifier: Programming Language :: Python :: Implementation
Classifier: Programming Language :: Python :: 2
Classifier: Programming Language :: Python :: 2.7
Classifier: Programming Language :: Python :: 3
Classifier: Programming Language :: Python :: 3.4
Classifier: Programming Language :: Python :: 3.5
Classifier: Programming Language :: Python :: 3.6
Classifier: Programming Language :: Python :: 3.7
Classifier: Topic :: Software Development :: Libraries
License-File: LICENSE
Requires-Dist: Crypto (>=1.4.1)
Requires-Dist: pycryptodome (>=3.9.7)
Requires-Dist: setuptools (>=66.1.1)
